pylkron/__info__.py
pylkron/__init__.py
pylkron/elkron_alarm.py
pylkron/elkron_client.py
pylkron-0.0.1.dist-info/METADATA
pylkron-0.0.1.dist-info/WHEEL
pylkron-0.0.1.dist-info/RECORD
