Metadata-Version: 2.4
Name: pyLkron
Version: 0.0.1
Summary: Python package to interact with Elkron Alarm devices
Author-email: Jacopo Libè <jacopo.libe@gmail.com>
Requires-Dist: requests
